jgib
tests
