Metadata-Version: 2.1
Name: jgib
Version: 6.0.2
Summary: A general-purpose python package for logging, event-emission, and other common code.
Home-page: https://github.com/rjgardnermd/jgib
Download-URL: https://github.com/rjgardnermd/jgib/archive/refs/tags/v6.0.2.tar.gz
Author: Jonathan Gardner
Author-email: rjgardnermd@gardnermoneygrowth.com
License: MIT
Keywords: PYTHON,IBKR,DTO,MODELS
Classifier: Development Status :: 3 - Alpha
Classifier: Intended Audience :: Developers
Classifier: Topic :: Software Development :: Build Tools
Classifier: License :: OSI Approved :: MIT License
Classifier: Programming Language :: Python :: 3.13
License-File: LICENSE.txt
Requires-Dist: pydantic
Requires-Dist: websockets
Requires-Dist: jgmd
